seatools/ioc/server/__init__.py
seatools/ioc/server/app.py
seatools/ioc/starters/fastapi/__init__.py
seatools/ioc/starters/fastapi/base.py
seatools_starter_web_fastapi-1.0.3.dist-info/METADATA
seatools_starter_web_fastapi-1.0.3.dist-info/WHEEL
seatools_starter_web_fastapi-1.0.3.dist-info/licenses/LICENSE
seatools_starter_web_fastapi-1.0.3.dist-info/RECORD
