Metadata-Version: 2.4
Name: seatools-starter-web-fastapi
Version: 1.0.3
Summary: Seatools Starter Web Fastapi
Project-URL: Homepage, https://github.com/seatools-py/seatools-starter-web-fastapi
Project-URL: Issues, https://github.com/seatools-py/seatools-starter-web-fastapi/issues
Author-email: seatools-py <521274311@qq.com>
License-Expression: MIT
License-File: LICENSE
Keywords: seatools>=1.0.41,starter
Classifier: License :: OSI Approved :: MIT License
Classifier: Operating System :: OS Independent
Classifier: Programming Language :: Python :: 3
Requires-Python: >=3.9
Requires-Dist: fastapi
Requires-Dist: seatools
